bucket_adapter/__init__.py
bucket_adapter/adapter.py
bucket_adapter/custom_blob.py
bucket_adapter/django_adapter.py
bucket_adapter/aws/__init__.py
bucket_adapter/aws/adapter.py
bucket_adapter/gcp/__init__.py
bucket_adapter/gcp/adapter.py
bucket_adapter-0.3.3.dist-info/LICENSE
bucket_adapter-0.3.3.dist-info/METADATA
bucket_adapter-0.3.3.dist-info/WHEEL
bucket_adapter-0.3.3.dist-info/top_level.txt
bucket_adapter-0.3.3.dist-info/RECORD
