Metadata-Version: 2.1
Name: bucket-adapter
Version: 0.3.3
Summary: A generic adapter for gcp/aws services to upload/downlaod files on bucket.
Home-page: https://github.com/shopistan/buckets_adapter
Author: Gohar Younas Malik
Author-email: goharyounas@gmail.com
License: UNKNOWN
Platform: UNKNOWN
Classifier: Programming Language :: Python :: 3.7
Classifier: License :: OSI Approved :: MIT License
Classifier: Intended Audience :: Developers
Classifier: Operating System :: OS Independent
Classifier: Topic :: Internet :: WWW/HTTP
Classifier: Topic :: Internet :: WWW/HTTP :: Dynamic Content
Requires-Python: >=3.7
Requires-Dist: Django (==3.0.8)
Requires-Dist: import-string
Requires-Dist: google-cloud
Requires-Dist: boto3
